pipeline_validator/__init__.py
pipeline_validator/config.py
pipeline_validator/decorators.py
pipeline_validator/exceptions.py
pipeline_validator/logger.py
pipeline_validator/pipeline_validator.py
pipeline_validator/fetchers/__init__.py
pipeline_validator/fetchers/brain_region_ontology_fetcher.py
pipeline_validator/tests/__init__.py
pipeline_validator/tests/test_config_validation.py
pipeline_validator/tests/test_rule_execution_validation.py
pipeline_validator/tests/utils.py
pipeline_validator/tests/mocks/brain_region_ontology.json
pipeline_validator/tests/mocks/rule_config.json
pipeline_validator/validator/__init__.py
pipeline_validator/validator/brain_region_tree_handler.py
pipeline_validator/validator/rule_validator.py
pipeline_validator/validator/schema_validator.py
pipeline_validator/validator/validator.py
pipeline_validator/validator/schemas/rules_schema.json
bbp_atlas_pipeline_validator-0.4.0.dist-info/LICENSE.txt
bbp_atlas_pipeline_validator-0.4.0.dist-info/METADATA
bbp_atlas_pipeline_validator-0.4.0.dist-info/WHEEL
bbp_atlas_pipeline_validator-0.4.0.dist-info/top_level.txt
bbp_atlas_pipeline_validator-0.4.0.dist-info/RECORD
