Metadata-Version: 2.1
Name: bbp-atlas-pipeline-validator
Version: 0.4.0
Summary: A pipeline validator for Blue Brain Project
Author: Blue Brain Project, EPFL
Project-URL: Homepage, https://github.com/BlueBrain/bbp-atlas-pipeline-validator
Classifier: Programming Language :: Python :: 3
Classifier: License :: OSI Approved :: Apache Software License
Classifier: Operating System :: OS Independent
Classifier: Topic :: Software Development :: Libraries :: Python Modules
License-File: LICENSE.txt
Requires-Dist: jsonschema >=4.18.4
Requires-Dist: pytest >=7.4.0
Requires-Dist: requests >=2.31.0
Requires-Dist: bigtree[pandas] >=0.10.0
Requires-Dist: pyJWT >=2.6.0
Provides-Extra: dev
Requires-Dist: black >=23.7.0 ; extra == 'dev'
